aqorg/AqOrg.py
aqorg/__init__.py
aqorg/data/alcohol_demo.csv
aqorg/data/element.csv
aqorg/data/group_contribution_data.csv
aqorg/data/joback_groups.csv
aqorg-0.5.0.dist-info/licenses/LICENSE.txt
aqorg-0.5.0.dist-info/METADATA
aqorg-0.5.0.dist-info/WHEEL
aqorg-0.5.0.dist-info/top_level.txt
aqorg-0.5.0.dist-info/RECORD
