Metadata-Version: 2.4
Name: aqorg
Version: 0.5.0
Summary: Estimate thermodynamic properties of aqueous organic compounds
Author-email: Grayson Boyer <gmboyer@asu.edu>
License: MIT
Project-URL: Homepage, https://github.com/worm-portal/aqorg
Classifier: Programming Language :: Python :: 3
Classifier: License :: OSI Approved :: MIT License
Classifier: Operating System :: OS Independent
Requires-Python: >=3.10
License-File: LICENSE.txt
Requires-Dist: chemparse
Requires-Dist: pubchempy
Requires-Dist: sigfig
Requires-Dist: pandas
Requires-Dist: rdkit
Requires-Dist: wormutils
Dynamic: license-file
